runj/__init__.py
runj/__main__.py
runj/runj.py
runj/models/data.py
python_runj-1.0.2.dist-info/METADATA
python_runj-1.0.2.dist-info/WHEEL
python_runj-1.0.2.dist-info/entry_points.txt
python_runj-1.0.2.dist-info/licenses/LICENSE
python_runj-1.0.2.dist-info/RECORD
