Metadata-Version: 2.1
Name: python-runj
Version: 1.0.2
Summary: I just want to run a shell command from Python!
Author: Rudolph Pienaar
License-Expression: MIT
License-File: LICENSE
Requires-Python: >=3.10
